app_full_django/__init__.py
app_full_django/crear_app.py
crear_app_full_django_anyelser-0.1.1.dist-info/licenses/LICENSE
crear_app_full_django_anyelser-0.1.1.dist-info/METADATA
crear_app_full_django_anyelser-0.1.1.dist-info/WHEEL
crear_app_full_django_anyelser-0.1.1.dist-info/entry_points.txt
crear_app_full_django_anyelser-0.1.1.dist-info/top_level.txt
crear_app_full_django_anyelser-0.1.1.dist-info/RECORD
