Metadata-Version: 2.4
Name: crear_app_full_django_anyelser
Version: 0.1.1
Summary: Una librería para crear app mas personalizadas en django
Author-email: Anyelser <anyelserperez@gmail.com>
License-Expression: MIT
Project-URL: Homepage, https://github.com/anyelser1213/CrearAppFullDjango
Classifier: Programming Language :: Python :: 3
Classifier: Operating System :: OS Independent
Classifier: Framework :: Django
Classifier: Framework :: Django :: 5.0
License-File: LICENSE
Requires-Dist: Django>=5.0
Dynamic: license-file
